rustplus/__init__.py
rustplus/rust_api.py
rustplus/annotations/__init__.py
rustplus/annotations/chat_event.py
rustplus/annotations/command.py
rustplus/annotations/entity_event.py
rustplus/annotations/protobuf_event.py
rustplus/annotations/team_event.py
rustplus/commands/__init__.py
rustplus/commands/chat_command.py
rustplus/commands/chat_command_data.py
rustplus/commands/command_options.py
rustplus/events/__init__.py
rustplus/events/chat_event.py
rustplus/events/entity_event.py
rustplus/events/protobuf_event.py
rustplus/events/team_event.py
rustplus/exceptions/__init__.py
rustplus/exceptions/exceptions.py
rustplus/icons/__init__.py
rustplus/icons/airfield.png
rustplus/icons/arctic_base.png
rustplus/icons/bandit.png
rustplus/icons/barn.png
rustplus/icons/cargo.png
rustplus/icons/chinook.png
rustplus/icons/chinook_blades.png
rustplus/icons/crate.png
rustplus/icons/desert_base.png
rustplus/icons/dome.png
rustplus/icons/excavator.png
rustplus/icons/explosion.png
rustplus/icons/ferryterminal.png
rustplus/icons/fishing.png
rustplus/icons/harbour.png
rustplus/icons/icon.png
rustplus/icons/jungle_ziggurat.png
rustplus/icons/junkyard.png
rustplus/icons/large_oil_rig.png
rustplus/icons/launchsite.png
rustplus/icons/lighthouse.png
rustplus/icons/military_tunnels.png
rustplus/icons/mining_outpost.png
rustplus/icons/mining_quarry_hqm.png
rustplus/icons/mining_quarry_stone.png
rustplus/icons/mining_quarry_sulfur.png
rustplus/icons/missile_silo.png
rustplus/icons/outpost.png
rustplus/icons/oxums.png
rustplus/icons/patrol.png
rustplus/icons/power_plant.png
rustplus/icons/radtown.png
rustplus/icons/satellite.png
rustplus/icons/sewer.png
rustplus/icons/small_oil_rig.png
rustplus/icons/stables.png
rustplus/icons/supermarket.png
rustplus/icons/swamp.png
rustplus/icons/train.png
rustplus/icons/train_yard.png
rustplus/icons/underwater_lab.png
rustplus/icons/vending_machine.png
rustplus/icons/water_treatment.png
rustplus/identification/__init__.py
rustplus/identification/handler_list.py
rustplus-6.0.9.dist-info/licenses/LICENSE
rustplus-6.0.9.dist-info/METADATA
rustplus-6.0.9.dist-info/WHEEL
rustplus-6.0.9.dist-info/top_level.txt
rustplus-6.0.9.dist-info/RECORD
