Metadata-Version: 2.4
Name: rustplus
Version: 6.0.9
Summary: A python wrapper for the Rust Plus API
Home-page: https://github.com/olijeffers0n/rustplus
Author: olijeffers0n
License: MIT
Project-URL: Issue tracker, https://github.com/olijeffers0n/rustplus/issues
Requires-Python: >=3.8.0
License-File: LICENSE
Requires-Dist: websockets
Requires-Dist: Pillow
Requires-Dist: asyncio
Requires-Dist: rustPlusPushReceiver==0.6.1
Requires-Dist: http-ece
Requires-Dist: requests
Requires-Dist: numpy
Requires-Dist: scipy
Requires-Dist: betterproto==2.0.0b7
Dynamic: author
Dynamic: description
Dynamic: description-content-type
Dynamic: home-page
Dynamic: license
Dynamic: license-file
Dynamic: project-url
Dynamic: requires-dist
Dynamic: requires-python
Dynamic: summary
